Ranch-1.0.0.data/data/data/address-export.2016-11-04T11:23:46.588473.json
Ranch-1.0.0.data/scripts/ranch-download
Ranch-1.0.0.dist-info/DESCRIPTION.rst
Ranch-1.0.0.dist-info/METADATA
Ranch-1.0.0.dist-info/RECORD
Ranch-1.0.0.dist-info/WHEEL
Ranch-1.0.0.dist-info/metadata.json
Ranch-1.0.0.dist-info/top_level.txt
ranch/__init__.py
ranch/address.py
ranch/json.py
ranch/specs.py
