Metadata-Version: 2.0
Name: Ranch
Version: 1.0.0
Summary: Ranch does addressing in Python
Home-page: https://github.com/3DHubs/ranch
Author: Martijn Arts
Author-email: martijn@3dhubs.com
License: UNKNOWN
Platform: UNKNOWN
Classifier: Development Status :: 4 - Beta
Classifier: License :: OSI Approved :: Apache Software License
Classifier: Programming Language :: Python :: 3.5
Classifier: Programming Language :: Python :: 3 :: Only
Requires-Dist: beautifulsoup4
Requires-Dist: flake8
Requires-Dist: requests
Requires-Dist: progressbar2
Requires-Dist: percache
